HelloPythonPackageblackhat721/__init__.py
HelloPythonPackageblackhat721/hello.py
hellopkgblackhat721-0.0.1.dist-info/LICENSE
hellopkgblackhat721-0.0.1.dist-info/METADATA
hellopkgblackhat721-0.0.1.dist-info/WHEEL
hellopkgblackhat721-0.0.1.dist-info/top_level.txt
hellopkgblackhat721-0.0.1.dist-info/RECORD
